fastfmri_toolbox/__init__.py
fastfmri_toolbox-0.1.1.dist-info/METADATA
fastfmri_toolbox-0.1.1.dist-info/WHEEL
fastfmri_toolbox-0.1.1.dist-info/top_level.txt
fastfmri_toolbox-0.1.1.dist-info/RECORD
